rabbitstew.py
rabbitstew-0.1.0.dist-info/zip-safe
rabbitstew-0.1.0.dist-info/top_level.txt
rabbitstew-0.1.0.dist-info/entry_points.txt
rabbitstew-0.1.0.dist-info/METADATA
rabbitstew-0.1.0.dist-info/DESCRIPTION.rst
rabbitstew-0.1.0.dist-info/metadata.json
rabbitstew-0.1.0.dist-info/WHEEL
rabbitstew-0.1.0.dist-info/RECORD
