Metadata-Version: 2.0
Name: rabbitstew
Version: 0.1.0
Summary: A command-line tool for publishing messages to RabbitMQ
Home-page: https://github.com/gmr/rabbitstew
Author: Gavin M. Roy
Author-email: gavinr@aweber.com
License: Copyright (c) 2015 Gavin M. Roy
Requires-Dist: rabbitpy (>=0.25.0)
